CSMTP/CSMTP.py
CSMTP/__init__.py
CSMTP-1.0.1.dist-info/METADATA
CSMTP-1.0.1.dist-info/WHEEL
CSMTP-1.0.1.dist-info/top_level.txt
CSMTP-1.0.1.dist-info/RECORD
